lib_x17_log-1.0.3.dist-info/licenses/LICENSE
xlog/__init__.py
xlog/base/__init__.py
xlog/base/component.py
xlog/base/tests/__init__.py
xlog/base/tests/test_class_component_all.py
xlog/event/__init__.py
xlog/event/base.py
xlog/event/logging.py
xlog/event/procs.py
xlog/event/tests/__init__.py
xlog/event/tests/test_class_base_all.py
xlog/event/tests/test_class_log_all.py
xlog/event/tests/test_class_procs_all.py
xlog/format/__init__.py
xlog/format/base.py
xlog/format/colorjson.py
xlog/format/colortext.py
xlog/format/colortree.py
xlog/format/json.py
xlog/format/text.py
xlog/format/tree.py
xlog/format/tests/__init__.py
xlog/format/tests/test_class_colorjson_all.py
xlog/format/tests/test_class_colortext_all.py
xlog/format/tests/test_class_colortree_all.py
xlog/format/tests/test_class_json_all.py
xlog/format/tests/test_class_text_all.py
xlog/format/tests/test_class_tree_all.py
xlog/group/__init__.py
xlog/group/base.py
xlog/group/filegroup.py
xlog/group/loggroup.py
xlog/group/s3group.py
xlog/group/tests/__init__.py
xlog/group/tests/test_class_base_all.py
xlog/group/tests/test_class_filegroup_all.py
xlog/group/tests/test_class_loggroup_all.py
xlog/group/tests/test_class_s3_group_all.py
xlog/node/__init__.py
xlog/node/base.py
xlog/node/logging.py
xlog/node/tests/__init__.py
xlog/node/tests/test_class_logging_all.py
xlog/stream/__init__.py
xlog/stream/stream.py
xlog/stream/tests/__init__.py
xlog/stream/tests/test_class_stream_all.py
lib_x17_log-1.0.3.dist-info/METADATA
lib_x17_log-1.0.3.dist-info/WHEEL
lib_x17_log-1.0.3.dist-info/top_level.txt
lib_x17_log-1.0.3.dist-info/RECORD
