Metadata-Version: 2.4
Name: lib-x17-log
Version: 1.0.3
Summary: logging module for x17 ecosystem
Author-email: Xing Xing <x.xing.work@gmail.com>
License-Expression: MIT
Requires-Python: >=3.11
License-File: LICENSE
Requires-Dist: colorlog>=6.10
Requires-Dist: rich>=13.0
Requires-Dist: pytz>=2025
Provides-Extra: dev
Requires-Dist: pytest>=8.3; extra == "dev"
Requires-Dist: ruff>=0.13; extra == "dev"
Requires-Dist: setuptools; extra == "dev"
Requires-Dist: wheel; extra == "dev"
Requires-Dist: twine; extra == "dev"
Requires-Dist: build; extra == "dev"
Provides-Extra: aws
Requires-Dist: boto3>=1.28; extra == "aws"
Dynamic: license-file
